oha_shared/__init__.py
oha_shared/mediator/README.md
oha_shared/mediator/__init__.py
oha_shared/mediator/decorators.py
oha_shared/mediator/mediator.py
oha_shared/mediator/mediator_config.py
oha_shared/mediator/pipeline_behavior.py
oha_shared/mediator/request.py
oha_shared/mediator/request_handler.py
oha_shared/mediator/utils.py
oha_shared/orm/__init__.py
oha_shared/orm/databases/__init__.py
oha_shared/orm/databases/database.py
oha_shared/orm/databases/postgresql_connection.py
oha_shared/orm/exceptions.py
oha_shared/orm/mixins/__init__.py
oha_shared/orm/mixins/audit_mixin.py
oha_shared/orm/mixins/text_search_mixin.py
oha_shared/orm/models/__init__.py
oha_shared/orm/models/base_model.py
oha_shared/orm/repositories/__init__.py
oha_shared/orm/repositories/base_repository.py
oha_shared/orm/units/__init__.py
oha_shared/orm/units/unit_of_work.py
oha_shared-0.1.0.dist-info/METADATA
oha_shared-0.1.0.dist-info/WHEEL
oha_shared-0.1.0.dist-info/RECORD
