Metadata-Version: 2.3
Name: oha-shared
Version: 0.1.0
Summary: OHA shared package
Author: ishika
Author-email: ishika@knacklabs.ai
Requires-Python: >=3.13,<4.0
Classifier: Programming Language :: Python :: 3
Classifier: Programming Language :: Python :: 3.13
Requires-Dist: black (>=25.1.0,<26.0.0)
Requires-Dist: psycopg2-binary (>=2.9.10,<3.0.0)
Requires-Dist: ruff (>=0.12.11,<0.13.0)
Requires-Dist: sqlalchemy (>=2.0.0,<3.0.0)
Requires-Dist: wireup (>=2.0.1,<3.0.0)
